[
  {
    "rating": 94,
    "brand": "JBC Coffee Roasters",
    "bean": "Deri Kochoha Ethiopia",
    "reviewDate": "Jun 2016",
    "price": "$16.80/12 ounces",
    "brandUrl": "https://www.jbccoffeeroasters.com/90-plus-coffees",
    "beanUrl": "http://www.coffeereview.com/review/deri-kochoha-ethiopia-2/",
    "location": "Do not have records",
    "origin": "Do not have records",
    "roast": "Do not have records",
    "agtron": "",
    "aroma": "",
    "body": "",
    "withMilk": "",
    "logo": ""
  },
  {
    "rating": 94,
    "brand": "Barrington Coffee Roasting Co.",
    "bean": "Cachajinas Guatemala Huehuetenango",
    "reviewDate": "Jun 2016",
    "price": "$17.95/12 ounces",
    "brandUrl": "http://barringtoncoffee.com",
    "beanUrl":
      "http://www.coffeereview.com/review/cachajinas-guatemala-huehuetenango/",
    "location": "Lee, Massachusetts",
    "origin": "Huehuetenango Department, Guatemala",
    "roast": "Medium-Light",
    "agtron": "56/80",
    "aroma": "9",
    "body": "9",
    "withMilk": "0",
    "logo":
      "http://dlo9n43mpvj20faa12i3i3lh.wpengine.netdna-cdn.com/wp-content/uploads/2014/04/Marketplace-Barrington1.jpg"
  },
  {
    "rating": 94,
    "brand": "Campos Coffee",
    "bean": "Ethiopia Yirgacheffe Goro",
    "reviewDate": "Jun 2016",
    "price": "AUD $16.00/250 grams",
    "beanUrl": "http://www.coffeereview.com/review/ethiopia-yirgacheffe-goro/",
    "location": "Do not have records",
    "origin": "Do not have records",
    "roast": "Do not have records",
    "agtron": "",
    "aroma": "",
    "body": "",
    "withMilk": "",
    "logo": ""
  },
  {
    "rating": 95,
    "brand": "Dragonfly Coffee Roasters",
    "bean": "El Obraje Geisha",
    "reviewDate": "May 2016",
    "price": "$32.00/12 ounces",
    "brandUrl": "http://www.dragonflycoffeeroasters.com",
    "beanUrl": "http://www.coffeereview.com/review/el-obraje-geisha/",
    "location": "Do not have records",
    "origin": "Do not have records",
    "roast": "Do not have records",
    "agtron": "",
    "aroma": "",
    "body": "",
    "withMilk": "",
    "logo": ""
  },
  {
    "rating": 96,
    "brand": "Temple Coffee and Tea",
    "bean": "Ethiopia Yirgacheffe Reko",
    "reviewDate": "May 2016",
    "price": "$19.50/12 ounces",
    "brandUrl": "http://www.templecoffee.com",
    "beanUrl": "http://www.coffeereview.com/review/ethiopia-yirgacheffe-reko/",
    "location": "Do not have records",
    "origin": "Do not have records",
    "roast": "Do not have records",
    "agtron": "",
    "aroma": "",
    "body": "",
    "withMilk": "",
    "logo": ""
  },
  {
    "rating": 95,
    "brand": "Temple Coffee and Tea",
    "bean": "Costa Rica Alberto Guardia Bourbon Natural",
    "reviewDate": "May 2016",
    "price": "$20.50/12 ounces",
    "brandUrl": "http://www.templecoffee.com",
    "beanUrl": "http://www.coffeereview.com/review/14080/",
    "location": "Do not have records",
    "origin": "Do not have records",
    "roast": "Do not have records",
    "agtron": "",
    "aroma": "",
    "body": "",
    "withMilk": "",
    "logo": ""
  },
  {
    "rating": 94,
    "brand": "Red Rooster Coffee Roaster",
    "bean": "Colombia San Adolfo",
    "reviewDate": "May 2016",
    "price": "$17.00/12 ounces",
    "beanUrl": "http://www.coffeereview.com/review/colombia-san-adolfo/",
    "location": "Do not have records",
    "origin": "Do not have records",
    "roast": "Do not have records",
    "agtron": "0",
    "aroma": "",
    "body": "",
    "withMilk": "0",
    "logo": ""
  },
  {
    "rating": 94,
    "brand": "Hula Daddy",
    "bean": "Laura’s Reserve SL-28",
    "reviewDate": "May 2016",
    "price": "$39.95/8 ounces",
    "brandUrl": "http://www.huladaddy.com",
    "beanUrl": "http://www.coffeereview.com/review/lauras-reserve-sl-28-2/",
    "location": "Do not have records",
    "origin": "Do not have records",
    "roast": "Do not have records",
    "agtron": "",
    "aroma": "",
    "body": "",
    "withMilk": "",
    "logo": ""
  },
  {
    "rating": 94,
    "brand": "Revel Coffee",
    "bean": "Brazil Estancia Telese",
    "reviewDate": "May 2016",
    "price": "$13.25/12 ounces",
    "beanUrl": "http://www.coffeereview.com/review/brazil-estancia-telese/",
    "location": "Do not have records",
    "origin": "Do not have records",
    "roast": "Do not have records",
    "agtron": "",
    "aroma": "",
    "body": "",
    "withMilk": "",
    "logo": ""
  },
  {
    "rating": 94,
    "brand": "Willoughby's Coffee & Tea",
    "bean": "Brazil Fazenda Passeio Natural",
    "reviewDate": "May 2016",
    "price": "$13.99/16 ounces",
    "brandUrl": "http://www.willoughbyscoffee.com",
    "beanUrl":
      "http://www.coffeereview.com/review/brazil-fazenda-passeio-natural/",
    "location": "Do not have records",
    "origin": "Do not have records",
    "roast": "Do not have records",
    "agtron": "",
    "aroma": "",
    "body": "",
    "withMilk": "",
    "logo": ""
  },
  {
    "rating": 94,
    "brand": "Kakalove Café",
    "bean": "Kenya Nyeri Gatugi AA",
    "reviewDate": "Apr 2016",
    "price": "$500 NTD/16 ounces",
    "brandUrl": "http://www.kakalovecafe.com.tw/",
    "beanUrl": "http://www.coffeereview.com/review/kenya-nyeri-gatugi-aa/",
    "location": "Do not have records",
    "origin": "Do not have records",
    "roast": "Do not have records",
    "agtron": "",
    "aroma": "",
    "body": "",
    "withMilk": "",
    "logo": ""
  },
  {
    "rating": 95,
    "brand": "Bird Rock Coffee Roasters",
    "bean": "Panama La Esmeralda Bosque Geisha",
    "reviewDate": "Apr 2016",
    "price": "$50.00/8 ounces",
    "brandUrl": "http://www.birdrockcoffee.com",
    "beanUrl":
      "http://www.coffeereview.com/review/panama-la-esmeralda-bosque-geisha/",
    "location": "Do not have records",
    "origin": "Do not have records",
    "roast": "Do not have records",
    "agtron": "",
    "aroma": "",
    "body": "",
    "withMilk": "",
    "logo": ""
  },
  {
    "rating": 94,
    "brand": "The WestBean Coffee Roasers",
    "bean": "Ethiopia Yirgacheffe Kebele Kochore",
    "reviewDate": "Apr 2016",
    "price": "$28.00/16 ounces",
    "brandUrl": "http://www.thewestbean.com",
    "beanUrl":
      "http://www.coffeereview.com/review/ethiopia-yirgacheffe-kebele-kochore/",
    "location": "Do not have records",
    "origin": "Do not have records",
    "roast": "Do not have records",
    "agtron": "",
    "aroma": "",
    "body": "",
    "withMilk": "",
    "logo": ""
  },
  {
    "rating": 94,
    "brand": "Lexington Coffee Roasters",
    "bean": "El Sitio Ecuador",
    "reviewDate": "Apr 2016",
    "price": "$18.95/12 ounces",
    "brandUrl": "http://www.lexingtoncoffee.com",
    "beanUrl": "http://www.coffeereview.com/review/el-sitio-ecuador/",
    "location": "Do not have records",
    "origin": "Do not have records",
    "roast": "Do not have records",
    "agtron": "",
    "aroma": "",
    "body": "",
    "withMilk": "",
    "logo": ""
  },
  {
    "rating": 94,
    "brand": "JBC Coffee Roasters",
    "bean": "Harfusa Espresso",
    "reviewDate": "Apr 2016",
    "price": "$17.80/12 ounces",
    "brandUrl": "https://www.jbccoffeeroasters.com/90-plus-coffees",
    "beanUrl": "http://www.coffeereview.com/review/harfusa-espresso/",
    "location": "Do not have records",
    "origin": "Do not have records",
    "roast": "Do not have records",
    "agtron": "",
    "aroma": "",
    "body": "",
    "withMilk": "",
    "logo": ""
  },
  {
    "rating": 94,
    "brand": "Lexington Coffee Roasters",
    "bean": "SOPACDI Congo",
    "reviewDate": "Apr 2016",
    "price": "$17.95/12 ounces",
    "brandUrl": "http://www.lexingtoncoffee.com",
    "beanUrl": "http://www.coffeereview.com/review/sopacdi-congo/",
    "location": "Do not have records",
    "origin": "Do not have records",
    "roast": "Do not have records",
    "agtron": "",
    "aroma": "",
    "body": "",
    "withMilk": "",
    "logo": ""
  },
  {
    "rating": 95,
    "brand": "Big Shoulders Coffee",
    "bean": "Reserve Panama Geisha Hacienda La Esmeralda",
    "reviewDate": "Apr 2016",
    "price": "$53.00/8 ounces",
    "brandUrl": "http://www.bigshoulderscoffee.com",
    "beanUrl":
      "http://www.coffeereview.com/review/reserve-panama-geisha-hacienda-la-esmeralda/",
    "location": "Chicago, Illinois",
    "origin": "Boquete growing region, western Panama",
    "roast": "Medium-Light",
    "agtron": "54/86",
    "aroma": "9",
    "body": "9",
    "withMilk": "0",
    "logo":
      "http://dlo9n43mpvj20faa12i3i3lh.wpengine.netdna-cdn.com/wp-content/uploads/2016/02/Big_Sho_Logo-150x150.jpg"
  },
  {
    "rating": 94,
    "brand": "Red Rooster Coffee Roaster",
    "bean": "Competition Blend",
    "reviewDate": "Mar 2016",
    "price": "$16.99/12 ounces",
    "beanUrl": "http://www.coffeereview.com/review/competition-blend/",
    "location": "Do not have records",
    "origin": "Do not have records",
    "roast": "Do not have records",
    "agtron": "0",
    "aroma": "",
    "body": "",
    "withMilk": "0",
    "logo": ""
  },
  {
    "rating": 94,
    "brand": "Cafe Virtuoso",
    "bean": "Bean Brain Reserve Suke Quto Ethiopia Sidamo Espresso",
    "reviewDate": "Mar 2016",
    "price": "$19.00/12 ounces",
    "beanUrl":
      "http://www.coffeereview.com/review/bean-brain-reserve-suke-quto-ethiopia-sidamo-espresso/",
    "location": "Do not have records",
    "origin": "Do not have records",
    "roast": "Do not have records",
    "agtron": "0",
    "aroma": "",
    "body": "",
    "withMilk": "0",
    "logo": ""
  },
  {
    "rating": 96,
    "brand": "Barrington Coffee Roasting Co.",
    "bean": "Hambela Ethiopia",
    "reviewDate": "Mar 2016",
    "price": "$17.45/12 ounces",
    "brandUrl": "http://barringtoncoffee.com",
    "beanUrl": "http://www.coffeereview.com/review/hambela-ethiopia/",
    "location": "Lee, Massachusetts",
    "origin":
      "Hambela Wamena District, Guji Zone, Oromia Region, southern Ethiopia",
    "roast": "Medium-Light",
    "agtron": "57/82",
    "aroma": "10",
    "body": "9",
    "withMilk": "0",
    "logo":
      "http://dlo9n43mpvj20faa12i3i3lh.wpengine.netdna-cdn.com/wp-content/uploads/2016/03/13_375x375-150x150.jpg"
  }
]
